{
  "hash": "cc2c8401",
  "browserHash": "93cb0405",
  "optimized": {
    "@vue/devtools-api": {
      "src": "../../../../node_modules/@vue/devtools-api/lib/esm/index.js",
      "file": "@vue_devtools-api.js",
      "fileHash": "758f933e",
      "needsInterop": false
    },
    "@vuepress/shared": {
      "src": "../../../../node_modules/@vuepress/shared/dist/index.js",
      "file": "@vuepress_shared.js",
      "fileHash": "d34835d7",
      "needsInterop": false
    },
    "vue": {
      "src": "../../../../node_modules/vue/dist/vue.runtime.esm-bundler.js",
      "file": "vue.js",
      "fileHash": "8155c183",
      "needsInterop": false
    },
    "vue-router": {
      "src": "../../../../node_modules/vue-router/dist/vue-router.esm-bundler.js",
      "file": "vue-router.js",
      "fileHash": "7567b660",
      "needsInterop": false
    },
    "axios": {
      "src": "../../../../node_modules/axios/index.js",
      "file": "axios.js",
      "fileHash": "77df1ee1",
      "needsInterop": false
    },
    "store": {
      "src": "../../../../node_modules/store/dist/store.legacy.js",
      "file": "store.js",
      "fileHash": "7d800bdc",
      "needsInterop": true
    },
    "aplayer": {
      "src": "../../../../node_modules/aplayer/dist/APlayer.min.js",
      "file": "aplayer.js",
      "fileHash": "5d931813",
      "needsInterop": true
    }
  },
  "chunks": {
    "chunk-RFQTXRIF": {
      "file": "chunk-RFQTXRIF.js"
    },
    "chunk-AQDTH7GJ": {
      "file": "chunk-AQDTH7GJ.js"
    },
    "chunk-DDKVHXSX": {
      "file": "chunk-DDKVHXSX.js"
    },
    "chunk-RSJERJUL": {
      "file": "chunk-RSJERJUL.js"
    }
  }
}